[
  {
    "displayWidth": 700,
    "displayHeight": 1000
  },
  {
    "CemeteryCode": "10-15",
    "Coordinates": [
      [
        {"x": 36, "y": 895},
        {"x": 68, "y": 895},
        {"x": 68, "y": 862},
        {"x": 36, "y": 862}
      ]
    ]
  },
  {
    "CemeteryCode": "10-13",
    "Coordinates": [
      [
        {"x": 68, "y": 895},
        {"x": 100, "y": 895},
        {"x": 100, "y": 862},
        {"x": 68, "y": 862}
      ]
    ]
  },
  {
    "CemeteryCode": "10-12",
    "Coordinates": [
      [
        {"x": 100, "y": 895},
        {"x": 132, "y": 895},
        {"x": 132, "y": 862},
        {"x": 100, "y": 862}
      ]
    ]
  },
  {
    "CemeteryCode": "10-11",
    "Coordinates": [
      [
        {"x": 132, "y": 895},
        {"x": 164, "y": 895},
        {"x": 164, "y": 862},
        {"x": 132, "y": 862}
      ]
    ]
  },
  {
    "CemeteryCode": "10-10",
    "Coordinates": [
      [
        {"x": 164, "y": 895},
        {"x": 196, "y": 895},
        {"x": 196, "y": 862},
        {"x": 164, "y": 862}
      ]
    ]
  },
  {
    "CemeteryCode": "10-09",
    "Coordinates": [
      [
        {"x": 196, "y": 895},
        {"x": 228, "y": 895},
        {"x": 228, "y": 862},
        {"x": 196, "y": 862}
      ]
    ]
  },
  {
    "CemeteryCode": "10-08",
    "Coordinates": [
      [
        {"x": 228, "y": 895},
        {"x": 260, "y": 895},
        {"x": 260, "y": 862},
        {"x": 228, "y": 862}
      ]
    ]
  },
  {
    "CemeteryCode": "10-07",
    "Coordinates": [
      [
        {"x": 260, "y": 895},
        {"x": 292, "y": 895},
        {"x": 292, "y": 862},
        {"x": 260, "y": 862}
      ]
    ]
  },
  {
    "CemeteryCode": "10-06",
    "Coordinates": [
      [
        {"x": 292, "y": 895},
        {"x": 324, "y": 895},
        {"x": 324, "y": 862},
        {"x": 292, "y": 862}
      ]
    ]
  },
  {
    "CemeteryCode": "10-05",
    "Coordinates": [
      [
        {"x": 324, "y": 895},
        {"x": 356, "y": 895},
        {"x": 356, "y": 862},
        {"x": 324, "y": 862}
      ]
    ]
  },
  {
    "CemeteryCode": "10-03",
    "Coordinates": [
      [
        {"x": 356, "y": 895},
        {"x": 388, "y": 895},
        {"x": 388, "y": 862},
        {"x": 356, "y": 862}
      ]
    ]
  },
  {
    "CemeteryCode": "10-02",
    "Coordinates": [
      [
        {"x": 388, "y": 895},
        {"x": 420, "y": 895},
        {"x": 420, "y": 862},
        {"x": 388, "y": 862}
      ]
    ]
  },
  {
    "CemeteryCode": "10-01",
    "Coordinates": [
      [
        {"x": 420, "y": 895},
        {"x": 452, "y": 895},
        {"x": 452, "y": 862},
        {"x": 420, "y": 862}
      ]
    ]
  },
  {
    "CemeteryCode": "09-15",
    "Coordinates": [
      [
        {"x": 36, "y": 848},
        {"x": 68, "y": 848},
        {"x": 68, "y": 815},
        {"x": 36, "y": 815}
      ]
    ]
  },
  {
    "CemeteryCode": "09-13",
    "Coordinates": [
      [
        {"x": 68, "y": 848},
        {"x": 100, "y": 848},
        {"x": 100, "y": 815},
        {"x": 68, "y": 815}
      ]
    ]
  },
  {
    "CemeteryCode": "09-12",
    "Coordinates": [
      [
        {"x": 100, "y": 848},
        {"x": 132, "y": 848},
        {"x": 132, "y": 815},
        {"x": 100, "y": 815}
      ]
    ]
  },
  {
    "CemeteryCode": "09-11",
    "Coordinates": [
      [
        {"x": 132, "y": 848},
        {"x": 164, "y": 848},
        {"x": 164, "y": 815},
        {"x": 132, "y": 815}
      ]
    ]
  },
  {
    "CemeteryCode": "09-10",
    "Coordinates": [
      [
        {"x": 164, "y": 848},
        {"x": 196, "y": 848},
        {"x": 196, "y": 815},
        {"x": 164, "y": 815}
      ]
    ]
  },
  {
    "CemeteryCode": "09-09",
    "Coordinates": [
      [
        {"x": 196, "y": 848},
        {"x": 228, "y": 848},
        {"x": 228, "y": 815},
        {"x": 196, "y": 815}
      ]
    ]
  },
  {
    "CemeteryCode": "09-08",
    "Coordinates": [
      [
        {"x": 228, "y": 848},
        {"x": 260, "y": 848},
        {"x": 260, "y": 815},
        {"x": 228, "y": 815}
      ]
    ]
  },
  {
    "CemeteryCode": "09-07",
    "Coordinates": [
      [
        {"x": 260, "y": 848},
        {"x": 292, "y": 848},
        {"x": 292, "y": 815},
        {"x": 260, "y": 815}
      ]
    ]
  },
  {
    "CemeteryCode": "09-06",
    "Coordinates": [
      [
        {"x": 292, "y": 848},
        {"x": 324, "y": 848},
        {"x": 324, "y": 815},
        {"x": 292, "y": 815}
      ]
    ]
  },
  {
    "CemeteryCode": "09-05",
    "Coordinates": [
      [
        {"x": 324, "y": 848},
        {"x": 356, "y": 848},
        {"x": 356, "y": 815},
        {"x": 324, "y": 815}
      ]
    ]
  },
  {
    "CemeteryCode": "09-03",
    "Coordinates": [
      [
        {"x": 356, "y": 848},
        {"x": 388, "y": 848},
        {"x": 388, "y": 815},
        {"x": 356, "y": 815}
      ]
    ]
  },
  {
    "CemeteryCode": "09-02",
    "Coordinates": [
      [
        {"x": 388, "y": 848},
        {"x": 420, "y": 848},
        {"x": 420, "y": 815},
        {"x": 388, "y": 815}
      ]
    ]
  },
  {
    "CemeteryCode": "09-01",
    "Coordinates": [
      [
        {"x": 420, "y": 848},
        {"x": 452, "y": 848},
        {"x": 452, "y": 815},
        {"x": 420, "y": 815}
      ]
    ]
  },
  {
    "CemeteryCode": "08-15",
    "Coordinates": [
      [
        {"x": 36, "y": 801},
        {"x": 68, "y": 801},
        {"x": 68, "y": 768},
        {"x": 36, "y": 768}
      ]
    ]
  },
  {
    "CemeteryCode": "08-13",
    "Coordinates": [
      [
        {"x": 68, "y": 801},
        {"x": 100, "y": 801},
        {"x": 100, "y": 768},
        {"x": 68, "y": 768}
      ]
    ]
  },
  {
    "CemeteryCode": "08-12",
    "Coordinates": [
      [
        {"x": 100, "y": 801},
        {"x": 132, "y": 801},
        {"x": 132, "y": 768},
        {"x": 100, "y": 768}
      ]
    ]
  },
  {
    "CemeteryCode": "08-11",
    "Coordinates": [
      [
        {"x": 132, "y": 801},
        {"x": 164, "y": 801},
        {"x": 164, "y": 768},
        {"x": 132, "y": 768}
      ]
    ]
  },
  {
    "CemeteryCode": "08-10",
    "Coordinates": [
      [
        {"x": 164, "y": 801},
        {"x": 196, "y": 801},
        {"x": 196, "y": 768},
        {"x": 164, "y": 768}
      ]
    ]
  },
  {
    "CemeteryCode": "08-09",
    "Coordinates": [
      [
        {"x": 196, "y": 801},
        {"x": 228, "y": 801},
        {"x": 228, "y": 768},
        {"x": 196, "y": 768}
      ]
    ]
  },
  {
    "CemeteryCode": "08-08",
    "Coordinates": [
      [
        {"x": 228, "y": 801},
        {"x": 260, "y": 801},
        {"x": 260, "y": 768},
        {"x": 228, "y": 768}
      ]
    ]
  },
  {
    "CemeteryCode": "08-07",
    "Coordinates": [
      [
        {"x": 260, "y": 801},
        {"x": 292, "y": 801},
        {"x": 292, "y": 768},
        {"x": 260, "y": 768}
      ]
    ]
  },
  {
    "CemeteryCode": "08-06",
    "Coordinates": [
      [
        {"x": 292, "y": 801},
        {"x": 324, "y": 801},
        {"x": 324, "y": 768},
        {"x": 292, "y": 768}
      ]
    ]
  },
  {
    "CemeteryCode": "08-05",
    "Coordinates": [
      [
        {"x": 324, "y": 801},
        {"x": 356, "y": 801},
        {"x": 356, "y": 768},
        {"x": 324, "y": 768}
      ]
    ]
  },
  {
    "CemeteryCode": "08-03",
    "Coordinates": [
      [
        {"x": 356, "y": 801},
        {"x": 388, "y": 801},
        {"x": 388, "y": 768},
        {"x": 356, "y": 768}
      ]
    ]
  },
  {
    "CemeteryCode": "08-02",
    "Coordinates": [
      [
        {"x": 388, "y": 801},
        {"x": 420, "y": 801},
        {"x": 420, "y": 768},
        {"x": 388, "y": 768}
      ]
    ]
  },
  {
    "CemeteryCode": "08-01",
    "Coordinates": [
      [
        {"x": 420, "y": 801},
        {"x": 452, "y": 801},
        {"x": 452, "y": 768},
        {"x": 420, "y": 768}
      ]
    ]
  },
  {
    "CemeteryCode": "-",
    "Coordinates": [
      [
        {"x": 0, "y": 1000},
        {"x": 0, "y": 1000},
        {"x": 0, "y": 1000},
        {"x": 0, "y": 1000}
      ]
    ]
  },
  {
    "CemeteryCode": "-",
    "Coordinates": [
      [
        {"x": 0, "y": 1000},
        {"x": 0, "y": 1000},
        {"x": 0, "y": 1000},
        {"x": 0, "y": 1000}
      ]
    ]
  },
  {
    "CemeteryCode": "-",
    "Coordinates": [
      [
        {"x": 0, "y": 1000},
        {"x": 0, "y": 1000},
        {"x": 0, "y": 1000},
        {"x": 0, "y": 1000}
      ]
    ]
  },
  {
    "CemeteryCode": "-",
    "Coordinates": [
      [
        {"x": 0, "y": 1000},
        {"x": 0, "y": 1000},
        {"x": 0, "y": 1000},
        {"x": 0, "y": 1000}
      ]
    ]
  },
  {
    "CemeteryCode": "-",
    "Coordinates": [
      [
        {"x": 0, "y": 1000},
        {"x": 0, "y": 1000},
        {"x": 0, "y": 1000},
        {"x": 0, "y": 1000}
      ]
    ]
  },
  {
    "CemeteryCode": "-",
    "Coordinates": [
      [
        {"x": 0, "y": 1000},
        {"x": 0, "y": 1000},
        {"x": 0, "y": 1000},
        {"x": 0, "y": 1000}
      ]
    ]
  },
  {
    "CemeteryCode": "-",
    "Coordinates": [
      [
        {"x": 0, "y": 1000},
        {"x": 0, "y": 1000},
        {"x": 0, "y": 1000},
        {"x": 0, "y": 1000}
      ]
    ]
  },
  {
    "CemeteryCode": "-",
    "Coordinates": [
      [
        {"x": 0, "y": 1000},
        {"x": 0, "y": 1000},
        {"x": 0, "y": 1000},
        {"x": 0, "y": 1000}
      ]
    ]
  },
  {
    "CemeteryCode": "-",
    "Coordinates": [
      [
        {"x": 0, "y": 1000},
        {"x": 0, "y": 1000},
        {"x": 0, "y": 1000},
        {"x": 0, "y": 1000}
      ]
    ]
  },
  {
    "CemeteryCode": "-",
    "Coordinates": [
      [
        {"x": 0, "y": 1000},
        {"x": 0, "y": 1000},
        {"x": 0, "y": 1000},
        {"x": 0, "y": 1000}
      ]
    ]
  },
  {
    "CemeteryCode": "-",
    "Coordinates": [
      [
        {"x": 0, "y": 1000},
        {"x": 0, "y": 1000},
        {"x": 0, "y": 1000},
        {"x": 0, "y": 1000}
      ]
    ]
  },
  {
    "CemeteryCode": "-",
    "Coordinates": [
      [
        {"x": 0, "y": 1000},
        {"x": 0, "y": 1000},
        {"x": 0, "y": 1000},
        {"x": 0, "y": 1000}
      ]
    ]
  },
  {
    "CemeteryCode": "-",
    "Coordinates": [
      [
        {"x": 0, "y": 1000},
        {"x": 0, "y": 1000},
        {"x": 0, "y": 1000},
        {"x": 0, "y": 1000}
      ]
    ]
  },
  {
    "CemeteryCode": "-",
    "Coordinates": [
      [
        {"x": 0, "y": 1000},
        {"x": 0, "y": 1000},
        {"x": 0, "y": 1000},
        {"x": 0, "y": 1000}
      ]
    ]
  },
  {
    "CemeteryCode": "-",
    "Coordinates": [
      [
        {"x": 0, "y": 1000},
        {"x": 0, "y": 1000},
        {"x": 0, "y": 1000},
        {"x": 0, "y": 1000}
      ]
    ]
  },
  {
    "CemeteryCode": "-",
    "Coordinates": [
      [
        {"x": 0, "y": 1000},
        {"x": 0, "y": 1000},
        {"x": 0, "y": 1000},
        {"x": 0, "y": 1000}
      ]
    ]
  },
  {
    "CemeteryCode": "-",
    "Coordinates": [
      [
        {"x": 0, "y": 1000},
        {"x": 0, "y": 1000},
        {"x": 0, "y": 1000},
        {"x": 0, "y": 1000}
      ]
    ]
  },
  {
    "CemeteryCode": "-",
    "Coordinates": [
      [
        {"x": 0, "y": 1000},
        {"x": 0, "y": 1000},
        {"x": 0, "y": 1000},
        {"x": 0, "y": 1000}
      ]
    ]
  },
  {
    "CemeteryCode": "-",
    "Coordinates": [
      [
        {"x": 0, "y": 1000},
        {"x": 0, "y": 1000},
        {"x": 0, "y": 1000},
        {"x": 0, "y": 1000}
      ]
    ]
  },
  {
    "CemeteryCode": "-",
    "Coordinates": [
      [
        {"x": 0, "y": 1000},
        {"x": 0, "y": 1000},
        {"x": 0, "y": 1000},
        {"x": 0, "y": 1000}
      ]
    ]
  },
  {
    "CemeteryCode": "-",
    "Coordinates": [
      [
        {"x": 0, "y": 1000},
        {"x": 0, "y": 1000},
        {"x": 0, "y": 1000},
        {"x": 0, "y": 1000}
      ]
    ]
  },
  {
    "CemeteryCode": "-",
    "Coordinates": [
      [
        {"x": 0, "y": 1000},
        {"x": 0, "y": 1000},
        {"x": 0, "y": 1000},
        {"x": 0, "y": 1000}
      ]
    ]
  },
  {
    "CemeteryCode": "-",
    "Coordinates": [
      [
        {"x": 0, "y": 1000},
        {"x": 0, "y": 1000},
        {"x": 0, "y": 1000},
        {"x": 0, "y": 1000}
      ]
    ]
  },
  {
    "CemeteryCode": "-",
    "Coordinates": [
      [
        {"x": 0, "y": 1000},
        {"x": 0, "y": 1000},
        {"x": 0, "y": 1000},
        {"x": 0, "y": 1000}
      ]
    ]
  },
  {
    "CemeteryCode": "-",
    "Coordinates": [
      [
        {"x": 0, "y": 1000},
        {"x": 0, "y": 1000},
        {"x": 0, "y": 1000},
        {"x": 0, "y": 1000}
      ]
    ]
  },
  {
    "CemeteryCode": "-",
    "Coordinates": [
      [
        {"x": 0, "y": 1000},
        {"x": 0, "y": 1000},
        {"x": 0, "y": 1000},
        {"x": 0, "y": 1000}
      ]
    ]
  },
  {
    "CemeteryCode": "-",
    "Coordinates": [
      [
        {"x": 0, "y": 1000},
        {"x": 0, "y": 1000},
        {"x": 0, "y": 1000},
        {"x": 0, "y": 1000}
      ]
    ]
  },
  {
    "CemeteryCode": "-",
    "Coordinates": [
      [
        {"x": 0, "y": 1000},
        {"x": 0, "y": 1000},
        {"x": 0, "y": 1000},
        {"x": 0, "y": 1000}
      ]
    ]
  },
  {
    "CemeteryCode": "-",
    "Coordinates": [
      [
        {"x": 0, "y": 1000},
        {"x": 0, "y": 1000},
        {"x": 0, "y": 1000},
        {"x": 0, "y": 1000}
      ]
    ]
  },
  {
    "CemeteryCode": "-",
    "Coordinates": [
      [
        {"x": 0, "y": 1000},
        {"x": 0, "y": 1000},
        {"x": 0, "y": 1000},
        {"x": 0, "y": 1000}
      ]
    ]
  },
  {
    "CemeteryCode": "-",
    "Coordinates": [
      [
        {"x": 0, "y": 1000},
        {"x": 0, "y": 1000},
        {"x": 0, "y": 1000},
        {"x": 0, "y": 1000}
      ]
    ]
  },
  {
    "CemeteryCode": "-",
    "Coordinates": [
      [
        {"x": 0, "y": 1000},
        {"x": 0, "y": 1000},
        {"x": 0, "y": 1000},
        {"x": 0, "y": 1000}
      ]
    ]
  },
  {
    "CemeteryCode": "-",
    "Coordinates": [
      [
        {"x": 0, "y": 1000},
        {"x": 0, "y": 1000},
        {"x": 0, "y": 1000},
        {"x": 0, "y": 1000}
      ]
    ]
  },
  {
    "CemeteryCode": "-",
    "Coordinates": [
      [
        {"x": 0, "y": 1000},
        {"x": 0, "y": 1000},
        {"x": 0, "y": 1000},
        {"x": 0, "y": 1000}
      ]
    ]
  },
  {
    "CemeteryCode": "-",
    "Coordinates": [
      [
        {"x": 0, "y": 1000},
        {"x": 0, "y": 1000},
        {"x": 0, "y": 1000},
        {"x": 0, "y": 1000}
      ]
    ]
  },
  {
    "CemeteryCode": "-",
    "Coordinates": [
      [
        {"x": 0, "y": 1000},
        {"x": 0, "y": 1000},
        {"x": 0, "y": 1000},
        {"x": 0, "y": 1000}
      ]
    ]
  },
  {
    "CemeteryCode": "-",
    "Coordinates": [
      [
        {"x": 0, "y": 1000},
        {"x": 0, "y": 1000},
        {"x": 0, "y": 1000},
        {"x": 0, "y": 1000}
      ]
    ]
  },
  {
    "CemeteryCode": "-",
    "Coordinates": [
      [
        {"x": 0, "y": 1000},
        {"x": 0, "y": 1000},
        {"x": 0, "y": 1000},
        {"x": 0, "y": 1000}
      ]
    ]
  },
  {
    "CemeteryCode": "-",
    "Coordinates": [
      [
        {"x": 0, "y": 1000},
        {"x": 0, "y": 1000},
        {"x": 0, "y": 1000},
        {"x": 0, "y": 1000}
      ]
    ]
  },
  {
    "CemeteryCode": "-",
    "Coordinates": [
      [
        {"x": 0, "y": 1000},
        {"x": 0, "y": 1000},
        {"x": 0, "y": 1000},
        {"x": 0, "y": 1000}
      ]
    ]
  },
  {
    "CemeteryCode": "-",
    "Coordinates": [
      [
        {"x": 0, "y": 1000},
        {"x": 0, "y": 1000},
        {"x": 0, "y": 1000},
        {"x": 0, "y": 1000}
      ]
    ]
  },
  {
    "CemeteryCode": "-",
    "Coordinates": [
      [
        {"x": 0, "y": 1000},
        {"x": 0, "y": 1000},
        {"x": 0, "y": 1000},
        {"x": 0, "y": 1000}
      ]
    ]
  },
  {
    "CemeteryCode": "-",
    "Coordinates": [
      [
        {"x": 0, "y": 1000},
        {"x": 0, "y": 1000},
        {"x": 0, "y": 1000},
        {"x": 0, "y": 1000}
      ]
    ]
  },
  {
    "CemeteryCode": "-",
    "Coordinates": [
      [
        {"x": 0, "y": 1000},
        {"x": 0, "y": 1000},
        {"x": 0, "y": 1000},
        {"x": 0, "y": 1000}
      ]
    ]
  },
  {
    "CemeteryCode": "-",
    "Coordinates": [
      [
        {"x": 0, "y": 1000},
        {"x": 0, "y": 1000},
        {"x": 0, "y": 1000},
        {"x": 0, "y": 1000}
      ]
    ]
  },
  {
    "CemeteryCode": "-",
    "Coordinates": [
      [
        {"x": 0, "y": 1000},
        {"x": 0, "y": 1000},
        {"x": 0, "y": 1000},
        {"x": 0, "y": 1000}
      ]
    ]
  },
  {
    "CemeteryCode": "-",
    "Coordinates": [
      [
        {"x": 0, "y": 1000},
        {"x": 0, "y": 1000},
        {"x": 0, "y": 1000},
        {"x": 0, "y": 1000}
      ]
    ]
  },
  {
    "CemeteryCode": "-",
    "Coordinates": [
      [
        {"x": 0, "y": 1000},
        {"x": 0, "y": 1000},
        {"x": 0, "y": 1000},
        {"x": 0, "y": 1000}
      ]
    ]
  },
  {
    "CemeteryCode": "-",
    "Coordinates": [
      [
        {"x": 0, "y": 1000},
        {"x": 0, "y": 1000},
        {"x": 0, "y": 1000},
        {"x": 0, "y": 1000}
      ]
    ]
  },
  {
    "CemeteryCode": "-",
    "Coordinates": [
      [
        {"x": 0, "y": 1000},
        {"x": 0, "y": 1000},
        {"x": 0, "y": 1000},
        {"x": 0, "y": 1000}
      ]
    ]
  },
  {
    "CemeteryCode": "-",
    "Coordinates": [
      [
        {"x": 0, "y": 1000},
        {"x": 0, "y": 1000},
        {"x": 0, "y": 1000},
        {"x": 0, "y": 1000}
      ]
    ]
  },
  {
    "CemeteryCode": "-",
    "Coordinates": [
      [
        {"x": 0, "y": 1000},
        {"x": 0, "y": 1000},
        {"x": 0, "y": 1000},
        {"x": 0, "y": 1000}
      ]
    ]
  },
  {
    "CemeteryCode": "-",
    "Coordinates": [
      [
        {"x": 0, "y": 1000},
        {"x": 0, "y": 1000},
        {"x": 0, "y": 1000},
        {"x": 0, "y": 1000}
      ]
    ]
  },
  {
    "CemeteryCode": "-",
    "Coordinates": [
      [
        {"x": 0, "y": 1000},
        {"x": 0, "y": 1000},
        {"x": 0, "y": 1000},
        {"x": 0, "y": 1000}
      ]
    ]
  },
  {
    "CemeteryCode": "-",
    "Coordinates": [
      [
        {"x": 0, "y": 1000},
        {"x": 0, "y": 1000},
        {"x": 0, "y": 1000},
        {"x": 0, "y": 1000}
      ]
    ]
  },
  {
    "CemeteryCode": "-",
    "Coordinates": [
      [
        {"x": 0, "y": 1000},
        {"x": 0, "y": 1000},
        {"x": 0, "y": 1000},
        {"x": 0, "y": 1000}
      ]
    ]
  },
  {
    "CemeteryCode": "-",
    "Coordinates": [
      [
        {"x": 0, "y": 1000},
        {"x": 0, "y": 1000},
        {"x": 0, "y": 1000},
        {"x": 0, "y": 1000}
      ]
    ]
  },
  {
    "CemeteryCode": "-",
    "Coordinates": [
      [
        {"x": 0, "y": 1000},
        {"x": 0, "y": 1000},
        {"x": 0, "y": 1000},
        {"x": 0, "y": 1000}
      ]
    ]
  },
  {
    "CemeteryCode": "-",
    "Coordinates": [
      [
        {"x": 0, "y": 1000},
        {"x": 0, "y": 1000},
        {"x": 0, "y": 1000},
        {"x": 0, "y": 1000}
      ]
    ]
  },
  {
    "CemeteryCode": "-",
    "Coordinates": [
      [
        {"x": 0, "y": 1000},
        {"x": 0, "y": 1000},
        {"x": 0, "y": 1000},
        {"x": 0, "y": 1000}
      ]
    ]
  },
  {
    "CemeteryCode": "-",
    "Coordinates": [
      [
        {"x": 0, "y": 1000},
        {"x": 0, "y": 1000},
        {"x": 0, "y": 1000},
        {"x": 0, "y": 1000}
      ]
    ]
  },
  {
    "CemeteryCode": "-",
    "Coordinates": [
      [
        {"x": 0, "y": 1000},
        {"x": 0, "y": 1000},
        {"x": 0, "y": 1000},
        {"x": 0, "y": 1000}
      ]
    ]
  },
  {
    "CemeteryCode": "-",
    "Coordinates": [
      [
        {"x": 0, "y": 1000},
        {"x": 0, "y": 1000},
        {"x": 0, "y": 1000},
        {"x": 0, "y": 1000}
      ]
    ]
  },
  {
    "CemeteryCode": "-",
    "Coordinates": [
      [
        {"x": 0, "y": 1000},
        {"x": 0, "y": 1000},
        {"x": 0, "y": 1000},
        {"x": 0, "y": 1000}
      ]
    ]
  },
  {
    "CemeteryCode": "-",
    "Coordinates": [
      [
        {"x": 0, "y": 1000},
        {"x": 0, "y": 1000},
        {"x": 0, "y": 1000},
        {"x": 0, "y": 1000}
      ]
    ]
  },
  {
    "CemeteryCode": "-",
    "Coordinates": [
      [
        {"x": 0, "y": 1000},
        {"x": 0, "y": 1000},
        {"x": 0, "y": 1000},
        {"x": 0, "y": 1000}
      ]
    ]
  },
  {
    "CemeteryCode": "-",
    "Coordinates": [
      [
        {"x": 0, "y": 1000},
        {"x": 0, "y": 1000},
        {"x": 0, "y": 1000},
        {"x": 0, "y": 1000}
      ]
    ]
  },
  {
    "CemeteryCode": "-",
    "Coordinates": [
      [
        {"x": 0, "y": 1000},
        {"x": 0, "y": 1000},
        {"x": 0, "y": 1000},
        {"x": 0, "y": 1000}
      ]
    ]
  },
  {
    "CemeteryCode": "-",
    "Coordinates": [
      [
        {"x": 0, "y": 1000},
        {"x": 0, "y": 1000},
        {"x": 0, "y": 1000},
        {"x": 0, "y": 1000}
      ]
    ]
  },
  {
    "CemeteryCode": "-",
    "Coordinates": [
      [
        {"x": 0, "y": 1000},
        {"x": 0, "y": 1000},
        {"x": 0, "y": 1000},
        {"x": 0, "y": 1000}
      ]
    ]
  },
  {
    "CemeteryCode": "-",
    "Coordinates": [
      [
        {"x": 0, "y": 1000},
        {"x": 0, "y": 1000},
        {"x": 0, "y": 1000},
        {"x": 0, "y": 1000}
      ]
    ]
  },
  {
    "CemeteryCode": "-",
    "Coordinates": [
      [
        {"x": 0, "y": 1000},
        {"x": 0, "y": 1000},
        {"x": 0, "y": 1000},
        {"x": 0, "y": 1000}
      ]
    ]
  },
  {
    "CemeteryCode": "-",
    "Coordinates": [
      [
        {"x": 0, "y": 1000},
        {"x": 0, "y": 1000},
        {"x": 0, "y": 1000},
        {"x": 0, "y": 1000}
      ]
    ]
  },
  {
    "CemeteryCode": "-",
    "Coordinates": [
      [
        {"x": 0, "y": 1000},
        {"x": 0, "y": 1000},
        {"x": 0, "y": 1000},
        {"x": 0, "y": 1000}
      ]
    ]
  },
  {
    "CemeteryCode": "-",
    "Coordinates": [
      [
        {"x": 0, "y": 1000},
        {"x": 0, "y": 1000},
        {"x": 0, "y": 1000},
        {"x": 0, "y": 1000}
      ]
    ]
  },
  {
    "CemeteryCode": "-",
    "Coordinates": [
      [
        {"x": 0, "y": 1000},
        {"x": 0, "y": 1000},
        {"x": 0, "y": 1000},
        {"x": 0, "y": 1000}
      ]
    ]
  },
  {
    "CemeteryCode": "-",
    "Coordinates": [
      [
        {"x": 0, "y": 1000},
        {"x": 0, "y": 1000},
        {"x": 0, "y": 1000},
        {"x": 0, "y": 1000}
      ]
    ]
  },
  {
    "CemeteryCode": "-",
    "Coordinates": [
      [
        {"x": 0, "y": 1000},
        {"x": 0, "y": 1000},
        {"x": 0, "y": 1000},
        {"x": 0, "y": 1000}
      ]
    ]
  },
  {
    "CemeteryCode": "-",
    "Coordinates": [
      [
        {"x": 0, "y": 1000},
        {"x": 0, "y": 1000},
        {"x": 0, "y": 1000},
        {"x": 0, "y": 1000}
      ]
    ]
  },
  {
    "CemeteryCode": "-",
    "Coordinates": [
      [
        {"x": 0, "y": 1000},
        {"x": 0, "y": 1000},
        {"x": 0, "y": 1000},
        {"x": 0, "y": 1000}
      ]
    ]
  },
  {
    "CemeteryCode": "-",
    "Coordinates": [
      [
        {"x": 0, "y": 1000},
        {"x": 0, "y": 1000},
        {"x": 0, "y": 1000},
        {"x": 0, "y": 1000}
      ]
    ]
  },
  {
    "CemeteryCode": "-",
    "Coordinates": [
      [
        {"x": 0, "y": 1000},
        {"x": 0, "y": 1000},
        {"x": 0, "y": 1000},
        {"x": 0, "y": 1000}
      ]
    ]
  },
  {
    "CemeteryCode": "-",
    "Coordinates": [
      [
        {"x": 0, "y": 1000},
        {"x": 0, "y": 1000},
        {"x": 0, "y": 1000},
        {"x": 0, "y": 1000}
      ]
    ]
  },
  {
    "CemeteryCode": "-",
    "Coordinates": [
      [
        {"x": 0, "y": 1000},
        {"x": 0, "y": 1000},
        {"x": 0, "y": 1000},
        {"x": 0, "y": 1000}
      ]
    ]
  },
  {
    "CemeteryCode": "-",
    "Coordinates": [
      [
        {"x": 0, "y": 1000},
        {"x": 0, "y": 1000},
        {"x": 0, "y": 1000},
        {"x": 0, "y": 1000}
      ]
    ]
  },
  {
    "CemeteryCode": "-",
    "Coordinates": [
      [
        {"x": 0, "y": 1000},
        {"x": 0, "y": 1000},
        {"x": 0, "y": 1000},
        {"x": 0, "y": 1000}
      ]
    ]
  },
  {
    "CemeteryCode": "-",
    "Coordinates": [
      [
        {"x": 0, "y": 1000},
        {"x": 0, "y": 1000},
        {"x": 0, "y": 1000},
        {"x": 0, "y": 1000}
      ]
    ]
  },
  {
    "CemeteryCode": "-",
    "Coordinates": [
      [
        {"x": 0, "y": 1000},
        {"x": 0, "y": 1000},
        {"x": 0, "y": 1000},
        {"x": 0, "y": 1000}
      ]
    ]
  },
  {
    "CemeteryCode": "-",
    "Coordinates": [
      [
        {"x": 0, "y": 1000},
        {"x": 0, "y": 1000},
        {"x": 0, "y": 1000},
        {"x": 0, "y": 1000}
      ]
    ]
  },
  {
    "CemeteryCode": "-",
    "Coordinates": [
      [
        {"x": 0, "y": 1000},
        {"x": 0, "y": 1000},
        {"x": 0, "y": 1000},
        {"x": 0, "y": 1000}
      ]
    ]
  },
  {
    "CemeteryCode": "-",
    "Coordinates": [
      [
        {"x": 0, "y": 1000},
        {"x": 0, "y": 1000},
        {"x": 0, "y": 1000},
        {"x": 0, "y": 1000}
      ]
    ]
  },
  {
    "CemeteryCode": "-",
    "Coordinates": [
      [
        {"x": 0, "y": 1000},
        {"x": 0, "y": 1000},
        {"x": 0, "y": 1000},
        {"x": 0, "y": 1000}
      ]
    ]
  },
  {
    "CemeteryCode": "-",
    "Coordinates": [
      [
        {"x": 0, "y": 1000},
        {"x": 0, "y": 1000},
        {"x": 0, "y": 1000},
        {"x": 0, "y": 1000}
      ]
    ]
  },
  {
    "CemeteryCode": "-",
    "Coordinates": [
      [
        {"x": 0, "y": 1000},
        {"x": 0, "y": 1000},
        {"x": 0, "y": 1000},
        {"x": 0, "y": 1000}
      ]
    ]
  },
  {
    "CemeteryCode": "-",
    "Coordinates": [
      [
        {"x": 0, "y": 1000},
        {"x": 0, "y": 1000},
        {"x": 0, "y": 1000},
        {"x": 0, "y": 1000}
      ]
    ]
  },
  {
    "CemeteryCode": "-",
    "Coordinates": [
      [
        {"x": 0, "y": 1000},
        {"x": 0, "y": 1000},
        {"x": 0, "y": 1000},
        {"x": 0, "y": 1000}
      ]
    ]
  },
  {
    "CemeteryCode": "-",
    "Coordinates": [
      [
        {"x": 0, "y": 1000},
        {"x": 0, "y": 1000},
        {"x": 0, "y": 1000},
        {"x": 0, "y": 1000}
      ]
    ]
  },
  {
    "CemeteryCode": "-",
    "Coordinates": [
      [
        {"x": 0, "y": 1000},
        {"x": 0, "y": 1000},
        {"x": 0, "y": 1000},
        {"x": 0, "y": 1000}
      ]
    ]
  },
  {
    "CemeteryCode": "-",
    "Coordinates": [
      [
        {"x": 0, "y": 1000},
        {"x": 0, "y": 1000},
        {"x": 0, "y": 1000},
        {"x": 0, "y": 1000}
      ]
    ]
  },
  {
    "CemeteryCode": "-",
    "Coordinates": [
      [
        {"x": 0, "y": 1000},
        {"x": 0, "y": 1000},
        {"x": 0, "y": 1000},
        {"x": 0, "y": 1000}
      ]
    ]
  },
  {
    "CemeteryCode": "-",
    "Coordinates": [
      [
        {"x": 0, "y": 1000},
        {"x": 0, "y": 1000},
        {"x": 0, "y": 1000},
        {"x": 0, "y": 1000}
      ]
    ]
  },
  {
    "CemeteryCode": "-",
    "Coordinates": [
      [
        {"x": 0, "y": 1000},
        {"x": 0, "y": 1000},
        {"x": 0, "y": 1000},
        {"x": 0, "y": 1000}
      ]
    ]
  },
  {
    "CemeteryCode": "-",
    "Coordinates": [
      [
        {"x": 0, "y": 1000},
        {"x": 0, "y": 1000},
        {"x": 0, "y": 1000},
        {"x": 0, "y": 1000}
      ]
    ]
  },
  {
    "CemeteryCode": "-",
    "Coordinates": [
      [
        {"x": 0, "y": 1000},
        {"x": 0, "y": 1000},
        {"x": 0, "y": 1000},
        {"x": 0, "y": 1000}
      ]
    ]
  },
  {
    "CemeteryCode": "-",
    "Coordinates": [
      [
        {"x": 0, "y": 1000},
        {"x": 0, "y": 1000},
        {"x": 0, "y": 1000},
        {"x": 0, "y": 1000}
      ]
    ]
  },
  {
    "CemeteryCode": "-",
    "Coordinates": [
      [
        {"x": 0, "y": 1000},
        {"x": 0, "y": 1000},
        {"x": 0, "y": 1000},
        {"x": 0, "y": 1000}
      ]
    ]
  },
  {
    "CemeteryCode": "-",
    "Coordinates": [
      [
        {"x": 0, "y": 1000},
        {"x": 0, "y": 1000},
        {"x": 0, "y": 1000},
        {"x": 0, "y": 1000}
      ]
    ]
  },
  {
    "CemeteryCode": "-",
    "Coordinates": [
      [
        {"x": 0, "y": 1000},
        {"x": 0, "y": 1000},
        {"x": 0, "y": 1000},
        {"x": 0, "y": 1000}
      ]
    ]
  },
  {
    "CemeteryCode": "-",
    "Coordinates": [
      [
        {"x": 0, "y": 1000},
        {"x": 0, "y": 1000},
        {"x": 0, "y": 1000},
        {"x": 0, "y": 1000}
      ]
    ]
  },
  {
    "CemeteryCode": "-",
    "Coordinates": [
      [
        {"x": 0, "y": 1000},
        {"x": 0, "y": 1000},
        {"x": 0, "y": 1000},
        {"x": 0, "y": 1000}
      ]
    ]
  },
  {
    "CemeteryCode": "-",
    "Coordinates": [
      [
        {"x": 0, "y": 1000},
        {"x": 0, "y": 1000},
        {"x": 0, "y": 1000},
        {"x": 0, "y": 1000}
      ]
    ]
  },
  {
    "CemeteryCode": "-",
    "Coordinates": [
      [
        {"x": 0, "y": 1000},
        {"x": 0, "y": 1000},
        {"x": 0, "y": 1000},
        {"x": 0, "y": 1000}
      ]
    ]
  },
  {
    "CemeteryCode": "-",
    "Coordinates": [
      [
        {"x": 0, "y": 1000},
        {"x": 0, "y": 1000},
        {"x": 0, "y": 1000},
        {"x": 0, "y": 1000}
      ]
    ]
  },
  {
    "CemeteryCode": "-",
    "Coordinates": [
      [
        {"x": 0, "y": 1000},
        {"x": 0, "y": 1000},
        {"x": 0, "y": 1000},
        {"x": 0, "y": 1000}
      ]
    ]
  },
  {
    "CemeteryCode": "-",
    "Coordinates": [
      [
        {"x": 0, "y": 1000},
        {"x": 0, "y": 1000},
        {"x": 0, "y": 1000},
        {"x": 0, "y": 1000}
      ]
    ]
  },
  {
    "CemeteryCode": "-",
    "Coordinates": [
      [
        {"x": 0, "y": 1000},
        {"x": 0, "y": 1000},
        {"x": 0, "y": 1000},
        {"x": 0, "y": 1000}
      ]
    ]
  },
  {
    "CemeteryCode": "-",
    "Coordinates": [
      [
        {"x": 0, "y": 1000},
        {"x": 0, "y": 1000},
        {"x": 0, "y": 1000},
        {"x": 0, "y": 1000}
      ]
    ]
  },
  {
    "CemeteryCode": "-",
    "Coordinates": [
      [
        {"x": 0, "y": 1000},
        {"x": 0, "y": 1000},
        {"x": 0, "y": 1000},
        {"x": 0, "y": 1000}
      ]
    ]
  },
  {
    "CemeteryCode": "-",
    "Coordinates": [
      [
        {"x": 0, "y": 1000},
        {"x": 0, "y": 1000},
        {"x": 0, "y": 1000},
        {"x": 0, "y": 1000}
      ]
    ]
  },
  {
    "CemeteryCode": "-",
    "Coordinates": [
      [
        {"x": 0, "y": 1000},
        {"x": 0, "y": 1000},
        {"x": 0, "y": 1000},
        {"x": 0, "y": 1000}
      ]
    ]
  },
  {
    "CemeteryCode": "-",
    "Coordinates": [
      [
        {"x": 0, "y": 1000},
        {"x": 0, "y": 1000},
        {"x": 0, "y": 1000},
        {"x": 0, "y": 1000}
      ]
    ]
  },
  {
    "CemeteryCode": "-",
    "Coordinates": [
      [
        {"x": 0, "y": 1000},
        {"x": 0, "y": 1000},
        {"x": 0, "y": 1000},
        {"x": 0, "y": 1000}
      ]
    ]
  },
  {
    "CemeteryCode": "-",
    "Coordinates": [
      [
        {"x": 0, "y": 1000},
        {"x": 0, "y": 1000},
        {"x": 0, "y": 1000},
        {"x": 0, "y": 1000}
      ]
    ]
  }
]