[
  {
    "displayWidth": 500,
    "displayHeight": 750
  },
  {
    "CemeteryCode": "15-16",
    "Coordinates": [
      [
        {"x": 143, "y": 590},
        {"x": 169, "y": 590},
        {"x": 169, "y": 561},
        {"x": 143, "y": 561}
      ]
    ]
  },
  {
    "CemeteryCode": "15-15",
    "Coordinates": [
      [
        {"x": 169, "y": 590},
        {"x": 195, "y": 590},
        {"x": 195, "y": 561},
        {"x": 169, "y": 561}
      ]
    ]
  },
  {
    "CemeteryCode": "15-13",
    "Coordinates": [
      [
        {"x": 195, "y": 590},
        {"x": 221, "y": 590},
        {"x": 221, "y": 561},
        {"x": 195, "y": 561}
      ]
    ]
  },
  {
    "CemeteryCode": "15-12",
    "Coordinates": [
      [
        {"x": 221, "y": 590},
        {"x": 247, "y": 590},
        {"x": 247, "y": 561},
        {"x": 221, "y": 561}
      ]
    ]
  },
  {
    "CemeteryCode": "15-11",
    "Coordinates": [
      [
        {"x": 247, "y": 590},
        {"x": 273, "y": 590},
        {"x": 273, "y": 561},
        {"x": 247, "y": 561}
      ]
    ]
  },
  {
    "CemeteryCode": "15-10",
    "Coordinates": [
      [
        {"x": 273, "y": 590},
        {"x": 299, "y": 590},
        {"x": 299, "y": 561},
        {"x": 273, "y": 561}
      ]
    ]
  },
  {
    "CemeteryCode": "15-08",
    "Coordinates": [
      [
        {"x": 299, "y": 590},
        {"x": 325, "y": 590},
        {"x": 325, "y": 561},
        {"x": 299, "y": 561}
      ]
    ]
  },
  {
    "CemeteryCode": "15-07",
    "Coordinates": [
      [
        {"x": 325, "y": 590},
        {"x": 351, "y": 590},
        {"x": 351, "y": 561},
        {"x": 325, "y": 561}
      ]
    ]
  },
  {
    "CemeteryCode": "15-06",
    "Coordinates": [
      [
        {"x": 351, "y": 590},
        {"x": 377, "y": 590},
        {"x": 377, "y": 561},
        {"x": 351, "y": 561}
      ]
    ]
  },
  {
    "CemeteryCode": "15-05",
    "Coordinates": [
      [
        {"x": 377, "y": 590},
        {"x": 403, "y": 590},
        {"x": 403, "y": 561},
        {"x": 377, "y": 561}
      ]
    ]
  },
  {
    "CemeteryCode": "15-03",
    "Coordinates": [
      [
        {"x": 403, "y": 590},
        {"x": 429, "y": 590},
        {"x": 429, "y": 561},
        {"x": 403, "y": 561}
      ]
    ]
  },
  {
    "CemeteryCode": "15-02",
    "Coordinates": [
      [
        {"x": 429, "y": 590},
        {"x": 455, "y": 590},
        {"x": 455, "y": 561},
        {"x": 429, "y": 561}
      ]
    ]
  },
  {
    "CemeteryCode": "15-01",
    "Coordinates": [
      [
        {"x": 455, "y": 590},
        {"x": 481, "y": 590},
        {"x": 481, "y": 561},
        {"x": 455, "y": 561}
      ]
    ]
  },
  {
    "CemeteryCode": "13-17",
    "Coordinates": [
      [
        {"x": 117, "y": 552},
        {"x": 143, "y": 552},
        {"x": 143, "y": 523},
        {"x": 117, "y": 523}
      ]
    ]
  },
  {
    "CemeteryCode": "13-16",
    "Coordinates": [
      [
        {"x": 143, "y": 552},
        {"x": 169, "y": 552},
        {"x": 169, "y": 523},
        {"x": 143, "y": 523}
      ]
    ]
  },
  {
    "CemeteryCode": "13-15",
    "Coordinates": [
      [
        {"x": 169, "y": 552},
        {"x": 195, "y": 552},
        {"x": 195, "y": 523},
        {"x": 169, "y": 523}
      ]
    ]
  },
  {
    "CemeteryCode": "13-13",
    "Coordinates": [
      [
        {"x": 195, "y": 552},
        {"x": 221, "y": 552},
        {"x": 221, "y": 523},
        {"x": 195, "y": 523}
      ]
    ]
  },
  {
    "CemeteryCode": "13-12",
    "Coordinates": [
      [
        {"x": 221, "y": 552},
        {"x": 247, "y": 552},
        {"x": 247, "y": 523},
        {"x": 221, "y": 523}
      ]
    ]
  },
  {
    "CemeteryCode": "13-11",
    "Coordinates": [
      [
        {"x": 247, "y": 552},
        {"x": 273, "y": 552},
        {"x": 273, "y": 523},
        {"x": 247, "y": 523}
      ]
    ]
  },
  {
    "CemeteryCode": "13-10",
    "Coordinates": [
      [
        {"x": 273, "y": 552},
        {"x": 299, "y": 552},
        {"x": 299, "y": 523},
        {"x": 273, "y": 523}
      ]
    ]
  },
  {
    "CemeteryCode": "13-08",
    "Coordinates": [
      [
        {"x": 299, "y": 552},
        {"x": 325, "y": 552},
        {"x": 325, "y": 523},
        {"x": 299, "y": 523}
      ]
    ]
  },
  {
    "CemeteryCode": "13-07",
    "Coordinates": [
      [
        {"x": 325, "y": 552},
        {"x": 351, "y": 552},
        {"x": 351, "y": 523},
        {"x": 325, "y": 523}
      ]
    ]
  },
  {
    "CemeteryCode": "13-06",
    "Coordinates": [
      [
        {"x": 351, "y": 552},
        {"x": 377, "y": 552},
        {"x": 377, "y": 523},
        {"x": 351, "y": 523}
      ]
    ]
  },
  {
    "CemeteryCode": "13-05",
    "Coordinates": [
      [
        {"x": 377, "y": 552},
        {"x": 403, "y": 552},
        {"x": 403, "y": 523},
        {"x": 377, "y": 523}
      ]
    ]
  },
  {
    "CemeteryCode": "13-03",
    "Coordinates": [
      [
        {"x": 403, "y": 552},
        {"x": 429, "y": 552},
        {"x": 429, "y": 523},
        {"x": 403, "y": 523}
      ]
    ]
  },
  {
    "CemeteryCode": "13-02",
    "Coordinates": [
      [
        {"x": 429, "y": 552},
        {"x": 455, "y": 552},
        {"x": 455, "y": 523},
        {"x": 429, "y": 523}
      ]
    ]
  },
  {
    "CemeteryCode": "13-01",
    "Coordinates": [
      [
        {"x": 455, "y": 552},
        {"x": 481, "y": 552},
        {"x": 481, "y": 523},
        {"x": 455, "y": 523}
      ]
    ]
  },
  {
    "CemeteryCode": "12-17",
    "Coordinates": [
      [
        {"x": 117, "y": 513},
        {"x": 143, "y": 513},
        {"x": 143, "y": 484},
        {"x": 117, "y": 484}
      ]
    ]
  },
  {
    "CemeteryCode": "12-16",
    "Coordinates": [
      [
        {"x": 143, "y": 513},
        {"x": 169, "y": 513},
        {"x": 169, "y": 484},
        {"x": 143, "y": 484}
      ]
    ]
  },
  {
    "CemeteryCode": "12-15",
    "Coordinates": [
      [
        {"x": 169, "y": 513},
        {"x": 195, "y": 513},
        {"x": 195, "y": 484},
        {"x": 169, "y": 484}
      ]
    ]
  },
  {
    "CemeteryCode": "12-13",
    "Coordinates": [
      [
        {"x": 195, "y": 513},
        {"x": 221, "y": 513},
        {"x": 221, "y": 484},
        {"x": 195, "y": 484}
      ]
    ]
  },
  {
    "CemeteryCode": "12-12",
    "Coordinates": [
      [
        {"x": 221, "y": 513},
        {"x": 247, "y": 513},
        {"x": 247, "y": 484},
        {"x": 221, "y": 484}
      ]
    ]
  },
  {
    "CemeteryCode": "12-11",
    "Coordinates": [
      [
        {"x": 247, "y": 513},
        {"x": 273, "y": 513},
        {"x": 273, "y": 484},
        {"x": 247, "y": 484}
      ]
    ]
  },
  {
    "CemeteryCode": "12-10",
    "Coordinates": [
      [
        {"x": 273, "y": 513},
        {"x": 299, "y": 513},
        {"x": 299, "y": 484},
        {"x": 273, "y": 484}
      ]
    ]
  },
  {
    "CemeteryCode": "12-08",
    "Coordinates": [
      [
        {"x": 299, "y": 513},
        {"x": 325, "y": 513},
        {"x": 325, "y": 484},
        {"x": 299, "y": 484}
      ]
    ]
  },
  {
    "CemeteryCode": "12-07",
    "Coordinates": [
      [
        {"x": 325, "y": 513},
        {"x": 351, "y": 513},
        {"x": 351, "y": 484},
        {"x": 325, "y": 484}
      ]
    ]
  },
  {
    "CemeteryCode": "12-06",
    "Coordinates": [
      [
        {"x": 351, "y": 513},
        {"x": 377, "y": 513},
        {"x": 377, "y": 484},
        {"x": 351, "y": 484}
      ]
    ]
  },
  {
    "CemeteryCode": "12-05",
    "Coordinates": [
      [
        {"x": 377, "y": 513},
        {"x": 403, "y": 513},
        {"x": 403, "y": 484},
        {"x": 377, "y": 484}
      ]
    ]
  },
  {
    "CemeteryCode": "12-03",
    "Coordinates": [
      [
        {"x": 403, "y": 513},
        {"x": 429, "y": 513},
        {"x": 429, "y": 484},
        {"x": 403, "y": 484}
      ]
    ]
  },
  {
    "CemeteryCode": "12-02",
    "Coordinates": [
      [
        {"x": 429, "y": 513},
        {"x": 455, "y": 513},
        {"x": 455, "y": 484},
        {"x": 429, "y": 484}
      ]
    ]
  },
  {
    "CemeteryCode": "12-01",
    "Coordinates": [
      [
        {"x": 455, "y": 513},
        {"x": 481, "y": 513},
        {"x": 481, "y": 484},
        {"x": 455, "y": 484}
      ]
    ]
  },
  {
    "CemeteryCode": "11-17",
    "Coordinates": [
      [
        {"x": 117, "y": 475},
        {"x": 143, "y": 475},
        {"x": 143, "y": 446},
        {"x": 117, "y": 446}
      ]
    ]
  },
  {
    "CemeteryCode": "11-16",
    "Coordinates": [
      [
        {"x": 143, "y": 475},
        {"x": 169, "y": 475},
        {"x": 169, "y": 446},
        {"x": 143, "y": 446}
      ]
    ]
  },
  {
    "CemeteryCode": "11-15",
    "Coordinates": [
      [
        {"x": 169, "y": 475},
        {"x": 195, "y": 475},
        {"x": 195, "y": 446},
        {"x": 169, "y": 446}
      ]
    ]
  },
  {
    "CemeteryCode": "11-13",
    "Coordinates": [
      [
        {"x": 195, "y": 475},
        {"x": 221, "y": 475},
        {"x": 221, "y": 446},
        {"x": 195, "y": 446}
      ]
    ]
  },
  {
    "CemeteryCode": "11-12",
    "Coordinates": [
      [
        {"x": 221, "y": 475},
        {"x": 247, "y": 475},
        {"x": 247, "y": 446},
        {"x": 221, "y": 446}
      ]
    ]
  },
  {
    "CemeteryCode": "11-11",
    "Coordinates": [
      [
        {"x": 247, "y": 475},
        {"x": 273, "y": 475},
        {"x": 273, "y": 446},
        {"x": 247, "y": 446}
      ]
    ]
  },
  {
    "CemeteryCode": "11-10",
    "Coordinates": [
      [
        {"x": 273, "y": 475},
        {"x": 299, "y": 475},
        {"x": 299, "y": 446},
        {"x": 273, "y": 446}
      ]
    ]
  },
  {
    "CemeteryCode": "11-08",
    "Coordinates": [
      [
        {"x": 299, "y": 475},
        {"x": 325, "y": 475},
        {"x": 325, "y": 446},
        {"x": 299, "y": 446}
      ]
    ]
  },
  {
    "CemeteryCode": "11-07",
    "Coordinates": [
      [
        {"x": 325, "y": 475},
        {"x": 351, "y": 475},
        {"x": 351, "y": 446},
        {"x": 325, "y": 446}
      ]
    ]
  },
  {
    "CemeteryCode": "11-06",
    "Coordinates": [
      [
        {"x": 351, "y": 475},
        {"x": 377, "y": 475},
        {"x": 377, "y": 446},
        {"x": 351, "y": 446}
      ]
    ]
  },
  {
    "CemeteryCode": "11-05",
    "Coordinates": [
      [
        {"x": 377, "y": 475},
        {"x": 403, "y": 475},
        {"x": 403, "y": 446},
        {"x": 377, "y": 446}
      ]
    ]
  },
  {
    "CemeteryCode": "11-03",
    "Coordinates": [
      [
        {"x": 403, "y": 475},
        {"x": 429, "y": 475},
        {"x": 429, "y": 446},
        {"x": 403, "y": 446}
      ]
    ]
  },
  {
    "CemeteryCode": "11-02",
    "Coordinates": [
      [
        {"x": 429, "y": 475},
        {"x": 455, "y": 475},
        {"x": 455, "y": 446},
        {"x": 429, "y": 446}
      ]
    ]
  },
  {
    "CemeteryCode": "11-01",
    "Coordinates": [
      [
        {"x": 455, "y": 475},
        {"x": 481, "y": 475},
        {"x": 481, "y": 446},
        {"x": 455, "y": 446}
      ]
    ]
  },
  {
    "CemeteryCode": "10-17",
    "Coordinates": [
      [
        {"x": 117, "y": 436},
        {"x": 143, "y": 436},
        {"x": 143, "y": 407},
        {"x": 117, "y": 407}
      ]
    ]
  },
  {
    "CemeteryCode": "10-16",
    "Coordinates": [
      [
        {"x": 143, "y": 436},
        {"x": 169, "y": 436},
        {"x": 169, "y": 407},
        {"x": 143, "y": 407}
      ]
    ]
  },
  {
    "CemeteryCode": "10-15",
    "Coordinates": [
      [
        {"x": 169, "y": 436},
        {"x": 195, "y": 436},
        {"x": 195, "y": 407},
        {"x": 169, "y": 407}
      ]
    ]
  },
  {
    "CemeteryCode": "10-13",
    "Coordinates": [
      [
        {"x": 195, "y": 436},
        {"x": 221, "y": 436},
        {"x": 221, "y": 407},
        {"x": 195, "y": 407}
      ]
    ]
  },
  {
    "CemeteryCode": "10-12",
    "Coordinates": [
      [
        {"x": 221, "y": 436},
        {"x": 247, "y": 436},
        {"x": 247, "y": 407},
        {"x": 221, "y": 407}
      ]
    ]
  },
  {
    "CemeteryCode": "10-11",
    "Coordinates": [
      [
        {"x": 247, "y": 436},
        {"x": 273, "y": 436},
        {"x": 273, "y": 407},
        {"x": 247, "y": 407}
      ]
    ]
  },
  {
    "CemeteryCode": "10-10",
    "Coordinates": [
      [
        {"x": 273, "y": 436},
        {"x": 299, "y": 436},
        {"x": 299, "y": 407},
        {"x": 273, "y": 407}
      ]
    ]
  },
  {
    "CemeteryCode": "10-08",
    "Coordinates": [
      [
        {"x": 299, "y": 436},
        {"x": 325, "y": 436},
        {"x": 325, "y": 407},
        {"x": 299, "y": 407}
      ]
    ]
  },
  {
    "CemeteryCode": "10-07",
    "Coordinates": [
      [
        {"x": 325, "y": 436},
        {"x": 351, "y": 436},
        {"x": 351, "y": 407},
        {"x": 325, "y": 407}
      ]
    ]
  },
  {
    "CemeteryCode": "10-06",
    "Coordinates": [
      [
        {"x": 351, "y": 436},
        {"x": 377, "y": 436},
        {"x": 377, "y": 407},
        {"x": 351, "y": 407}
      ]
    ]
  },
  {
    "CemeteryCode": "10-05",
    "Coordinates": [
      [
        {"x": 377, "y": 436},
        {"x": 403, "y": 436},
        {"x": 403, "y": 407},
        {"x": 377, "y": 407}
      ]
    ]
  },
  {
    "CemeteryCode": "10-03",
    "Coordinates": [
      [
        {"x": 403, "y": 436},
        {"x": 429, "y": 436},
        {"x": 429, "y": 407},
        {"x": 403, "y": 407}
      ]
    ]
  },
  {
    "CemeteryCode": "10-02",
    "Coordinates": [
      [
        {"x": 429, "y": 436},
        {"x": 455, "y": 436},
        {"x": 455, "y": 407},
        {"x": 429, "y": 407}
      ]
    ]
  },
  {
    "CemeteryCode": "10-01",
    "Coordinates": [
      [
        {"x": 455, "y": 436},
        {"x": 481, "y": 436},
        {"x": 481, "y": 407},
        {"x": 455, "y": 407}
      ]
    ]
  },
  {
    "CemeteryCode": "08-17",
    "Coordinates": [
      [
        {"x": 117, "y": 398},
        {"x": 143, "y": 398},
        {"x": 143, "y": 369},
        {"x": 117, "y": 369}
      ]
    ]
  },
  {
    "CemeteryCode": "08-16",
    "Coordinates": [
      [
        {"x": 143, "y": 398},
        {"x": 169, "y": 398},
        {"x": 169, "y": 369},
        {"x": 143, "y": 369}
      ]
    ]
  },
  {
    "CemeteryCode": "08-15",
    "Coordinates": [
      [
        {"x": 169, "y": 398},
        {"x": 195, "y": 398},
        {"x": 195, "y": 369},
        {"x": 169, "y": 369}
      ]
    ]
  },
  {
    "CemeteryCode": "08-13",
    "Coordinates": [
      [
        {"x": 195, "y": 398},
        {"x": 221, "y": 398},
        {"x": 221, "y": 369},
        {"x": 195, "y": 369}
      ]
    ]
  },
  {
    "CemeteryCode": "08-12",
    "Coordinates": [
      [
        {"x": 221, "y": 398},
        {"x": 247, "y": 398},
        {"x": 247, "y": 369},
        {"x": 221, "y": 369}
      ]
    ]
  },
  {
    "CemeteryCode": "08-11",
    "Coordinates": [
      [
        {"x": 247, "y": 398},
        {"x": 273, "y": 398},
        {"x": 273, "y": 369},
        {"x": 247, "y": 369}
      ]
    ]
  },
  {
    "CemeteryCode": "08-10",
    "Coordinates": [
      [
        {"x": 273, "y": 398},
        {"x": 299, "y": 398},
        {"x": 299, "y": 369},
        {"x": 273, "y": 369}
      ]
    ]
  },
  {
    "CemeteryCode": "08-08",
    "Coordinates": [
      [
        {"x": 299, "y": 398},
        {"x": 325, "y": 398},
        {"x": 325, "y": 369},
        {"x": 299, "y": 369}
      ]
    ]
  },
  {
    "CemeteryCode": "08-07",
    "Coordinates": [
      [
        {"x": 325, "y": 398},
        {"x": 351, "y": 398},
        {"x": 351, "y": 369},
        {"x": 325, "y": 369}
      ]
    ]
  },
  {
    "CemeteryCode": "08-06",
    "Coordinates": [
      [
        {"x": 351, "y": 398},
        {"x": 377, "y": 398},
        {"x": 377, "y": 369},
        {"x": 351, "y": 369}
      ]
    ]
  },
  {
    "CemeteryCode": "08-05",
    "Coordinates": [
      [
        {"x": 377, "y": 398},
        {"x": 403, "y": 398},
        {"x": 403, "y": 369},
        {"x": 377, "y": 369}
      ]
    ]
  },
  {
    "CemeteryCode": "08-03",
    "Coordinates": [
      [
        {"x": 403, "y": 398},
        {"x": 429, "y": 398},
        {"x": 429, "y": 369},
        {"x": 403, "y": 369}
      ]
    ]
  },
  {
    "CemeteryCode": "08-02",
    "Coordinates": [
      [
        {"x": 429, "y": 398},
        {"x": 455, "y": 398},
        {"x": 455, "y": 369},
        {"x": 429, "y": 369}
      ]
    ]
  },
  {
    "CemeteryCode": "08-01",
    "Coordinates": [
      [
        {"x": 455, "y": 398},
        {"x": 481, "y": 398},
        {"x": 481, "y": 369},
        {"x": 455, "y": 369}
      ]
    ]
  },
  {
    "CemeteryCode": "07-17",
    "Coordinates": [
      [
        {"x": 117, "y": 359},
        {"x": 143, "y": 359},
        {"x": 143, "y": 330},
        {"x": 117, "y": 330}
      ]
    ]
  },
  {
    "CemeteryCode": "07-16",
    "Coordinates": [
      [
        {"x": 143, "y": 359},
        {"x": 169, "y": 359},
        {"x": 169, "y": 330},
        {"x": 143, "y": 330}
      ]
    ]
  },
  {
    "CemeteryCode": "07-15",
    "Coordinates": [
      [
        {"x": 169, "y": 359},
        {"x": 195, "y": 359},
        {"x": 195, "y": 330},
        {"x": 169, "y": 330}
      ]
    ]
  },
  {
    "CemeteryCode": "07-13",
    "Coordinates": [
      [
        {"x": 195, "y": 359},
        {"x": 221, "y": 359},
        {"x": 221, "y": 330},
        {"x": 195, "y": 330}
      ]
    ]
  },
  {
    "CemeteryCode": "07-12",
    "Coordinates": [
      [
        {"x": 221, "y": 359},
        {"x": 247, "y": 359},
        {"x": 247, "y": 330},
        {"x": 221, "y": 330}
      ]
    ]
  },
  {
    "CemeteryCode": "07-11",
    "Coordinates": [
      [
        {"x": 247, "y": 359},
        {"x": 273, "y": 359},
        {"x": 273, "y": 330},
        {"x": 247, "y": 330}
      ]
    ]
  },
  {
    "CemeteryCode": "07-10",
    "Coordinates": [
      [
        {"x": 273, "y": 359},
        {"x": 299, "y": 359},
        {"x": 299, "y": 330},
        {"x": 273, "y": 330}
      ]
    ]
  },
  {
    "CemeteryCode": "07-08",
    "Coordinates": [
      [
        {"x": 299, "y": 359},
        {"x": 325, "y": 359},
        {"x": 325, "y": 330},
        {"x": 299, "y": 330}
      ]
    ]
  },
  {
    "CemeteryCode": "07-07",
    "Coordinates": [
      [
        {"x": 325, "y": 359},
        {"x": 351, "y": 359},
        {"x": 351, "y": 330},
        {"x": 325, "y": 330}
      ]
    ]
  },
  {
    "CemeteryCode": "07-06",
    "Coordinates": [
      [
        {"x": 351, "y": 359},
        {"x": 377, "y": 359},
        {"x": 377, "y": 330},
        {"x": 351, "y": 330}
      ]
    ]
  },
  {
    "CemeteryCode": "07-05",
    "Coordinates": [
      [
        {"x": 377, "y": 359},
        {"x": 403, "y": 359},
        {"x": 403, "y": 330},
        {"x": 377, "y": 330}
      ]
    ]
  },
  {
    "CemeteryCode": "07-03",
    "Coordinates": [
      [
        {"x": 403, "y": 359},
        {"x": 429, "y": 359},
        {"x": 429, "y": 330},
        {"x": 403, "y": 330}
      ]
    ]
  },
  {
    "CemeteryCode": "07-02",
    "Coordinates": [
      [
        {"x": 429, "y": 359},
        {"x": 455, "y": 359},
        {"x": 455, "y": 330},
        {"x": 429, "y": 330}
      ]
    ]
  },
  {
    "CemeteryCode": "07-01",
    "Coordinates": [
      [
        {"x": 455, "y": 359},
        {"x": 481, "y": 359},
        {"x": 481, "y": 330},
        {"x": 455, "y": 330}
      ]
    ]
  },
  {
    "CemeteryCode": "06-17",
    "Coordinates": [
      [
        {"x": 117, "y": 321},
        {"x": 143, "y": 321},
        {"x": 143, "y": 292},
        {"x": 117, "y": 292}
      ]
    ]
  },
  {
    "CemeteryCode": "06-16",
    "Coordinates": [
      [
        {"x": 143, "y": 321},
        {"x": 169, "y": 321},
        {"x": 169, "y": 292},
        {"x": 143, "y": 292}
      ]
    ]
  },
  {
    "CemeteryCode": "06-15",
    "Coordinates": [
      [
        {"x": 169, "y": 321},
        {"x": 195, "y": 321},
        {"x": 195, "y": 292},
        {"x": 169, "y": 292}
      ]
    ]
  },
  {
    "CemeteryCode": "06-13",
    "Coordinates": [
      [
        {"x": 195, "y": 321},
        {"x": 221, "y": 321},
        {"x": 221, "y": 292},
        {"x": 195, "y": 292}
      ]
    ]
  },
  {
    "CemeteryCode": "06-12",
    "Coordinates": [
      [
        {"x": 221, "y": 321},
        {"x": 247, "y": 321},
        {"x": 247, "y": 292},
        {"x": 221, "y": 292}
      ]
    ]
  },
  {
    "CemeteryCode": "06-11",
    "Coordinates": [
      [
        {"x": 247, "y": 321},
        {"x": 273, "y": 321},
        {"x": 273, "y": 292},
        {"x": 247, "y": 292}
      ]
    ]
  },
  {
    "CemeteryCode": "06-10",
    "Coordinates": [
      [
        {"x": 273, "y": 321},
        {"x": 299, "y": 321},
        {"x": 299, "y": 292},
        {"x": 273, "y": 292}
      ]
    ]
  },
  {
    "CemeteryCode": "06-08",
    "Coordinates": [
      [
        {"x": 299, "y": 321},
        {"x": 325, "y": 321},
        {"x": 325, "y": 292},
        {"x": 299, "y": 292}
      ]
    ]
  },
  {
    "CemeteryCode": "06-07",
    "Coordinates": [
      [
        {"x": 325, "y": 321},
        {"x": 351, "y": 321},
        {"x": 351, "y": 292},
        {"x": 325, "y": 292}
      ]
    ]
  },
  {
    "CemeteryCode": "06-06",
    "Coordinates": [
      [
        {"x": 351, "y": 321},
        {"x": 377, "y": 321},
        {"x": 377, "y": 292},
        {"x": 351, "y": 292}
      ]
    ]
  },
  {
    "CemeteryCode": "06-05",
    "Coordinates": [
      [
        {"x": 377, "y": 321},
        {"x": 403, "y": 321},
        {"x": 403, "y": 292},
        {"x": 377, "y": 292}
      ]
    ]
  },
  {
    "CemeteryCode": "06-03",
    "Coordinates": [
      [
        {"x": 403, "y": 321},
        {"x": 429, "y": 321},
        {"x": 429, "y": 292},
        {"x": 403, "y": 292}
      ]
    ]
  },
  {
    "CemeteryCode": "06-02",
    "Coordinates": [
      [
        {"x": 429, "y": 321},
        {"x": 455, "y": 321},
        {"x": 455, "y": 292},
        {"x": 429, "y": 292}
      ]
    ]
  },
  {
    "CemeteryCode": "06-01",
    "Coordinates": [
      [
        {"x": 455, "y": 321},
        {"x": 481, "y": 321},
        {"x": 481, "y": 292},
        {"x": 455, "y": 292}
      ]
    ]
  },
  {
    "CemeteryCode": "05-17",
    "Coordinates": [
      [
        {"x": 117, "y": 282},
        {"x": 143, "y": 282},
        {"x": 143, "y": 253},
        {"x": 117, "y": 253}
      ]
    ]
  },
  {
    "CemeteryCode": "05-16",
    "Coordinates": [
      [
        {"x": 143, "y": 282},
        {"x": 169, "y": 282},
        {"x": 169, "y": 253},
        {"x": 143, "y": 253}
      ]
    ]
  },
  {
    "CemeteryCode": "05-15",
    "Coordinates": [
      [
        {"x": 169, "y": 282},
        {"x": 195, "y": 282},
        {"x": 195, "y": 253},
        {"x": 169, "y": 253}
      ]
    ]
  },
  {
    "CemeteryCode": "05-13",
    "Coordinates": [
      [
        {"x": 195, "y": 282},
        {"x": 221, "y": 282},
        {"x": 221, "y": 253},
        {"x": 195, "y": 253}
      ]
    ]
  },
  {
    "CemeteryCode": "05-12",
    "Coordinates": [
      [
        {"x": 221, "y": 282},
        {"x": 247, "y": 282},
        {"x": 247, "y": 253},
        {"x": 221, "y": 253}
      ]
    ]
  },
  {
    "CemeteryCode": "05-11",
    "Coordinates": [
      [
        {"x": 247, "y": 282},
        {"x": 273, "y": 282},
        {"x": 273, "y": 253},
        {"x": 247, "y": 253}
      ]
    ]
  },
  {
    "CemeteryCode": "05-10",
    "Coordinates": [
      [
        {"x": 273, "y": 282},
        {"x": 299, "y": 282},
        {"x": 299, "y": 253},
        {"x": 273, "y": 253}
      ]
    ]
  },
  {
    "CemeteryCode": "05-08",
    "Coordinates": [
      [
        {"x": 299, "y": 282},
        {"x": 325, "y": 282},
        {"x": 325, "y": 253},
        {"x": 299, "y": 253}
      ]
    ]
  },
  {
    "CemeteryCode": "05-07",
    "Coordinates": [
      [
        {"x": 325, "y": 282},
        {"x": 351, "y": 282},
        {"x": 351, "y": 253},
        {"x": 325, "y": 253}
      ]
    ]
  },
  {
    "CemeteryCode": "05-06",
    "Coordinates": [
      [
        {"x": 351, "y": 282},
        {"x": 377, "y": 282},
        {"x": 377, "y": 253},
        {"x": 351, "y": 253}
      ]
    ]
  },
  {
    "CemeteryCode": "05-05",
    "Coordinates": [
      [
        {"x": 377, "y": 282},
        {"x": 403, "y": 282},
        {"x": 403, "y": 253},
        {"x": 377, "y": 253}
      ]
    ]
  },
  {
    "CemeteryCode": "05-03",
    "Coordinates": [
      [
        {"x": 403, "y": 282},
        {"x": 429, "y": 282},
        {"x": 429, "y": 253},
        {"x": 403, "y": 253}
      ]
    ]
  },
  {
    "CemeteryCode": "05-02",
    "Coordinates": [
      [
        {"x": 429, "y": 282},
        {"x": 455, "y": 282},
        {"x": 455, "y": 253},
        {"x": 429, "y": 253}
      ]
    ]
  },
  {
    "CemeteryCode": "05-01",
    "Coordinates": [
      [
        {"x": 455, "y": 282},
        {"x": 481, "y": 282},
        {"x": 481, "y": 253},
        {"x": 455, "y": 253}
      ]
    ]
  },
  {
    "CemeteryCode": "03-17",
    "Coordinates": [
      [
        {"x": 117, "y": 244},
        {"x": 143, "y": 244},
        {"x": 143, "y": 215},
        {"x": 117, "y": 215}
      ]
    ]
  },
  {
    "CemeteryCode": "03-16",
    "Coordinates": [
      [
        {"x": 143, "y": 244},
        {"x": 169, "y": 244},
        {"x": 169, "y": 215},
        {"x": 143, "y": 215}
      ]
    ]
  },
  {
    "CemeteryCode": "03-15",
    "Coordinates": [
      [
        {"x": 169, "y": 244},
        {"x": 195, "y": 244},
        {"x": 195, "y": 215},
        {"x": 169, "y": 215}
      ]
    ]
  },
  {
    "CemeteryCode": "03-13",
    "Coordinates": [
      [
        {"x": 195, "y": 244},
        {"x": 221, "y": 244},
        {"x": 221, "y": 215},
        {"x": 195, "y": 215}
      ]
    ]
  },
  {
    "CemeteryCode": "03-12",
    "Coordinates": [
      [
        {"x": 221, "y": 244},
        {"x": 247, "y": 244},
        {"x": 247, "y": 215},
        {"x": 221, "y": 215}
      ]
    ]
  },
  {
    "CemeteryCode": "03-11",
    "Coordinates": [
      [
        {"x": 247, "y": 244},
        {"x": 273, "y": 244},
        {"x": 273, "y": 215},
        {"x": 247, "y": 215}
      ]
    ]
  },
  {
    "CemeteryCode": "03-10",
    "Coordinates": [
      [
        {"x": 273, "y": 244},
        {"x": 299, "y": 244},
        {"x": 299, "y": 215},
        {"x": 273, "y": 215}
      ]
    ]
  },
  {
    "CemeteryCode": "03-08",
    "Coordinates": [
      [
        {"x": 299, "y": 244},
        {"x": 325, "y": 244},
        {"x": 325, "y": 215},
        {"x": 299, "y": 215}
      ]
    ]
  },
  {
    "CemeteryCode": "03-07",
    "Coordinates": [
      [
        {"x": 325, "y": 244},
        {"x": 351, "y": 244},
        {"x": 351, "y": 215},
        {"x": 325, "y": 215}
      ]
    ]
  },
  {
    "CemeteryCode": "03-06",
    "Coordinates": [
      [
        {"x": 351, "y": 244},
        {"x": 377, "y": 244},
        {"x": 377, "y": 215},
        {"x": 351, "y": 215}
      ]
    ]
  },
  {
    "CemeteryCode": "03-05",
    "Coordinates": [
      [
        {"x": 377, "y": 244},
        {"x": 403, "y": 244},
        {"x": 403, "y": 215},
        {"x": 377, "y": 215}
      ]
    ]
  },
  {
    "CemeteryCode": "03-03",
    "Coordinates": [
      [
        {"x": 403, "y": 244},
        {"x": 429, "y": 244},
        {"x": 429, "y": 215},
        {"x": 403, "y": 215}
      ]
    ]
  },
  {
    "CemeteryCode": "03-02",
    "Coordinates": [
      [
        {"x": 429, "y": 244},
        {"x": 455, "y": 244},
        {"x": 455, "y": 215},
        {"x": 429, "y": 215}
      ]
    ]
  },
  {
    "CemeteryCode": "03-01",
    "Coordinates": [
      [
        {"x": 455, "y": 244},
        {"x": 481, "y": 244},
        {"x": 481, "y": 215},
        {"x": 455, "y": 215}
      ]
    ]
  },
  {
    "CemeteryCode": "02-17",
    "Coordinates": [
      [
        {"x": 117, "y": 205},
        {"x": 143, "y": 205},
        {"x": 143, "y": 176},
        {"x": 117, "y": 176}
      ]
    ]
  },
  {
    "CemeteryCode": "02-16",
    "Coordinates": [
      [
        {"x": 143, "y": 205},
        {"x": 169, "y": 205},
        {"x": 169, "y": 176},
        {"x": 143, "y": 176}
      ]
    ]
  },
  {
    "CemeteryCode": "02-15",
    "Coordinates": [
      [
        {"x": 169, "y": 205},
        {"x": 195, "y": 205},
        {"x": 195, "y": 176},
        {"x": 169, "y": 176}
      ]
    ]
  },
  {
    "CemeteryCode": "02-13",
    "Coordinates": [
      [
        {"x": 195, "y": 205},
        {"x": 221, "y": 205},
        {"x": 221, "y": 176},
        {"x": 195, "y": 176}
      ]
    ]
  },
  {
    "CemeteryCode": "02-12",
    "Coordinates": [
      [
        {"x": 221, "y": 205},
        {"x": 247, "y": 205},
        {"x": 247, "y": 176},
        {"x": 221, "y": 176}
      ]
    ]
  },
  {
    "CemeteryCode": "02-11",
    "Coordinates": [
      [
        {"x": 247, "y": 205},
        {"x": 273, "y": 205},
        {"x": 273, "y": 176},
        {"x": 247, "y": 176}
      ]
    ]
  },
  {
    "CemeteryCode": "02-10",
    "Coordinates": [
      [
        {"x": 273, "y": 205},
        {"x": 299, "y": 205},
        {"x": 299, "y": 176},
        {"x": 273, "y": 176}
      ]
    ]
  },
  {
    "CemeteryCode": "02-08",
    "Coordinates": [
      [
        {"x": 299, "y": 205},
        {"x": 325, "y": 205},
        {"x": 325, "y": 176},
        {"x": 299, "y": 176}
      ]
    ]
  },
  {
    "CemeteryCode": "02-07",
    "Coordinates": [
      [
        {"x": 325, "y": 205},
        {"x": 351, "y": 205},
        {"x": 351, "y": 176},
        {"x": 325, "y": 176}
      ]
    ]
  },
  {
    "CemeteryCode": "02-06",
    "Coordinates": [
      [
        {"x": 351, "y": 205},
        {"x": 377, "y": 205},
        {"x": 377, "y": 176},
        {"x": 351, "y": 176}
      ]
    ]
  },
  {
    "CemeteryCode": "02-05",
    "Coordinates": [
      [
        {"x": 377, "y": 205},
        {"x": 403, "y": 205},
        {"x": 403, "y": 176},
        {"x": 377, "y": 176}
      ]
    ]
  },
  {
    "CemeteryCode": "02-03",
    "Coordinates": [
      [
        {"x": 403, "y": 205},
        {"x": 429, "y": 205},
        {"x": 429, "y": 176},
        {"x": 403, "y": 176}
      ]
    ]
  },
  {
    "CemeteryCode": "02-02",
    "Coordinates": [
      [
        {"x": 429, "y": 205},
        {"x": 455, "y": 205},
        {"x": 455, "y": 176},
        {"x": 429, "y": 176}
      ]
    ]
  },
  {
    "CemeteryCode": "02-01",
    "Coordinates": [
      [
        {"x": 455, "y": 205},
        {"x": 481, "y": 205},
        {"x": 481, "y": 176},
        {"x": 455, "y": 176}
      ]
    ]
  },
  {
    "CemeteryCode": "01-16",
    "Coordinates": [
      [
        {"x": 117, "y": 167},
        {"x": 143, "y": 167},
        {"x": 143, "y": 138},
        {"x": 117, "y": 138}
      ]
    ]
  },
  {
    "CemeteryCode": "01-15",
    "Coordinates": [
      [
        {"x": 143, "y": 167},
        {"x": 169, "y": 167},
        {"x": 169, "y": 138},
        {"x": 143, "y": 138}
      ]
    ]
  },
  {
    "CemeteryCode": "01-13",
    "Coordinates": [
      [
        {"x": 169, "y": 167},
        {"x": 195, "y": 167},
        {"x": 195, "y": 138},
        {"x": 169, "y": 138}
      ]
    ]
  },
  {
    "CemeteryCode": "01-12",
    "Coordinates": [
      [
        {"x": 195, "y": 167},
        {"x": 221, "y": 167},
        {"x": 221, "y": 138},
        {"x": 195, "y": 138}
      ]
    ]
  },
  {
    "CemeteryCode": "01-11",
    "Coordinates": [
      [
        {"x": 221, "y": 167},
        {"x": 247, "y": 167},
        {"x": 247, "y": 138},
        {"x": 221, "y": 138}
      ]
    ]
  },
  {
    "CemeteryCode": "01-10",
    "Coordinates": [
      [
        {"x": 247, "y": 167},
        {"x": 273, "y": 167},
        {"x": 273, "y": 138},
        {"x": 247, "y": 138}
      ]
    ]
  },
  {
    "CemeteryCode": "01-08",
    "Coordinates": [
      [
        {"x": 273, "y": 167},
        {"x": 299, "y": 167},
        {"x": 299, "y": 138},
        {"x": 273, "y": 138}
      ]
    ]
  },
  {
    "CemeteryCode": "01-07",
    "Coordinates": [
      [
        {"x": 299, "y": 167},
        {"x": 325, "y": 167},
        {"x": 325, "y": 138},
        {"x": 299, "y": 138}
      ]
    ]
  },
  {
    "CemeteryCode": "01-06",
    "Coordinates": [
      [
        {"x": 325, "y": 167},
        {"x": 351, "y": 167},
        {"x": 351, "y": 138},
        {"x": 325, "y": 138}
      ]
    ]
  },
  {
    "CemeteryCode": "01-05",
    "Coordinates": [
      [
        {"x": 351, "y": 167},
        {"x": 377, "y": 167},
        {"x": 377, "y": 138},
        {"x": 351, "y": 138}
      ]
    ]
  },
  {
    "CemeteryCode": "01-03",
    "Coordinates": [
      [
        {"x": 377, "y": 167},
        {"x": 403, "y": 167},
        {"x": 403, "y": 138},
        {"x": 377, "y": 138}
      ]
    ]
  },
  {
    "CemeteryCode": "01-02",
    "Coordinates": [
      [
        {"x": 403, "y": 167},
        {"x": 429, "y": 167},
        {"x": 429, "y": 138},
        {"x": 403, "y": 138}
      ]
    ]
  },
  {
    "CemeteryCode": "01-01",
    "Coordinates": [
      [
        {"x": 429, "y": 167},
        {"x": 455, "y": 167},
        {"x": 455, "y": 138},
        {"x": 429, "y": 138}
      ]
    ]
  }
]